framework/qiga.py
qiea-1.0.0.dist-info/LICENSE
qiea-1.0.0.dist-info/METADATA
qiea-1.0.0.dist-info/WHEEL
qiea-1.0.0.dist-info/entry_points.txt
qiea-1.0.0.dist-info/top_level.txt
qiea-1.0.0.dist-info/RECORD
