Metadata-Version: 2.1
Name: qiea
Version: 1.0.0
Summary: A Python package for Quantum Inspired Evolutionary Algorithms.
Home-page: https://github.com/adhishagc/qiea
Author: Adhisha Gammanpila
Author-email: adhishagc@gmail.com
License: MIT
Platform: UNKNOWN
Classifier: License :: OSI Approved :: MIT License
Classifier: Programming Language :: Python :: 3
Classifier: Programming Language :: Python :: 3.7
Requires-Dist: qiskit
Requires-Dist: tsplib95
Requires-Dist: networkx
